zzzeeksphinx/__init__.py
zzzeeksphinx/autodoc_mods.py
zzzeeksphinx/dialect_info.py
zzzeeksphinx/extras.py
zzzeeksphinx/mako.py
zzzeeksphinx/render_pydomains.py
zzzeeksphinx/scss.py
zzzeeksphinx/sqlformatter.py
zzzeeksphinx/theme.py
zzzeeksphinx/toc.py
zzzeeksphinx/util.py
zzzeeksphinx/viewsource.py
zzzeeksphinx/themes/zsbase/genindex.mako
zzzeeksphinx/themes/zsbase/layout.mako
zzzeeksphinx/themes/zsbase/notfound.mako
zzzeeksphinx/themes/zsbase/page.mako
zzzeeksphinx/themes/zsbase/search.mako
zzzeeksphinx/themes/zsbase/static_base.mako
zzzeeksphinx/themes/zsbase/theme.conf
zzzeeksphinx/themes/zsmako/layout.mako
zzzeeksphinx/themes/zsmako/theme.conf
zzzeeksphinx/themes/zsmako/static/docs.css
zzzeeksphinx/themes/zzzeeksphinx/theme.conf
zzzeeksphinx/themes/zzzeeksphinx/static/deepalchemy.png
zzzeeksphinx/themes/zzzeeksphinx/static/deepalchemy_original.png
zzzeeksphinx/themes/zzzeeksphinx/static/detectmobile.js
zzzeeksphinx/themes/zzzeeksphinx/static/docs.scss
zzzeeksphinx/themes/zzzeeksphinx/static/dragons.png
zzzeeksphinx/themes/zzzeeksphinx/static/dragons_original.png
zzzeeksphinx/themes/zzzeeksphinx/static/init.js
zzzeeksphinx-1.2.3.dist-info/LICENSE
zzzeeksphinx-1.2.3.dist-info/METADATA
zzzeeksphinx-1.2.3.dist-info/WHEEL
zzzeeksphinx-1.2.3.dist-info/entry_points.txt
zzzeeksphinx-1.2.3.dist-info/top_level.txt
zzzeeksphinx-1.2.3.dist-info/RECORD
