Metadata-Version: 2.1
Name: zzzeeksphinx
Version: 1.2.3
Summary: Zzzeek's Sphinx Layout and Utilities.
Home-page: https://github.com/sqlalchemyorg/zzzeeksphinx
Author: Mike Bayer
Author-email: mike@zzzcomputing.com
License: MIT
Keywords: Sphinx
Platform: UNKNOWN
Classifier: Development Status :: 3 - Alpha
Classifier: Environment :: Console
Classifier: Intended Audience :: Developers
Classifier: Programming Language :: Python :: 3
Classifier: Topic :: Documentation
Requires-Dist: pyscss
Requires-Dist: mako
Requires-Dist: requests
